fluster/__init__.py
fluster/codec.py
fluster/decoder.py
fluster/fluster.py
fluster/main.py
fluster/test.py
fluster/test_suite.py
fluster/test_vector.py
fluster/utils.py
fluster/decoders/__init__.py
fluster/decoders/av1_aom.py
fluster/decoders/av1_dav1d.py
fluster/decoders/chromium.py
fluster/decoders/cros_codecs.py
fluster/decoders/dummy.py
fluster/decoders/ffmpeg.py
fluster/decoders/gstreamer.py
fluster/decoders/h264_jct_vt.py
fluster/decoders/h265_jct_vt.py
fluster/decoders/h266_vvc_vtm.py
fluster/decoders/h266_vvdec.py
fluster/decoders/iso_mpeg2_aac.py
fluster/decoders/iso_mpeg2_video.py
fluster/decoders/iso_mpeg4_aac.py
fluster/decoders/iso_mpeg4_aac_er.py
fluster/decoders/iso_mpeg4_video.py
fluster/decoders/libvpx.py
fluster/decoders/vk_video_decoder.py
fluster_conformance-0.6.0.data/data/share/fluster/test_suites/aac/MPEG2_AAC-ADIF.json
fluster_conformance-0.6.0.data/data/share/fluster/test_suites/aac/MPEG2_AAC-ADTS.json
fluster_conformance-0.6.0.data/data/share/fluster/test_suites/aac/MPEG4_AAC-ADIF.json
fluster_conformance-0.6.0.data/data/share/fluster/test_suites/aac/MPEG4_AAC-ADTS.json
fluster_conformance-0.6.0.data/data/share/fluster/test_suites/aac/MPEG4_AAC-MP4-ER.json
fluster_conformance-0.6.0.data/data/share/fluster/test_suites/aac/MPEG4_AAC-MP4.json
fluster_conformance-0.6.0.data/data/share/fluster/test_suites/av1/AV1-ARGON-PROFILE0-CORE-ANNEX-B.json
fluster_conformance-0.6.0.data/data/share/fluster/test_suites/av1/AV1-ARGON-PROFILE0-ERROR-NON-ANNEX-B.json
fluster_conformance-0.6.0.data/data/share/fluster/test_suites/av1/AV1-ARGON-PROFILE0-NON-ANNEX-B.json
fluster_conformance-0.6.0.data/data/share/fluster/test_suites/av1/AV1-ARGON-PROFILE0-STRESS-ANNEX-B.json
fluster_conformance-0.6.0.data/data/share/fluster/test_suites/av1/AV1-ARGON-PROFILE1-CORE-ANNEX-B.json
fluster_conformance-0.6.0.data/data/share/fluster/test_suites/av1/AV1-ARGON-PROFILE1-ERROR-NON-ANNEX-B.json
fluster_conformance-0.6.0.dist-info/LICENSE
fluster_conformance-0.6.0.dist-info/METADATA
fluster_conformance-0.6.0.dist-info/WHEEL
fluster_conformance-0.6.0.dist-info/entry_points.txt
fluster_conformance-0.6.0.dist-info/top_level.txt
fluster_conformance-0.6.0.dist-info/RECORD
