Metadata-Version: 2.1
Name: fluster-conformance
Version: 0.6.0
Summary: Testing framework for decoder conformance
Author-email: Andoni Morales Alastruey <amorales@fluendo.com>
Maintainer-email: Michalis Dimopoulos <mdimopoulos@fluendo.com>, Ruben Gonzalez <rgonzalez@fluendo.com>
License: GNU LESSER GENERAL PUBLIC LICENSE
Project-URL: Github repository, https://github.com/fluendo/fluster/
Classifier: Development Status :: 5 - Production/Stable
Classifier: Intended Audience :: Developers
Classifier: Intended Audience :: Telecommunications Industry
Classifier: License :: OSI Approved :: GNU Lesser General Public License v3 or later (LGPLv3+)
Classifier: Operating System :: POSIX :: Linux
Classifier: Programming Language :: Python :: 3
Classifier: Programming Language :: Python :: 3.7
Classifier: Programming Language :: Python :: 3.8
Classifier: Programming Language :: Python :: 3.9
Classifier: Programming Language :: Python :: 3.10
Classifier: Programming Language :: Python :: 3.11
Classifier: Programming Language :: Python :: 3.12
Classifier: Programming Language :: Python :: 3.13
Classifier: Topic :: Multimedia
Classifier: Topic :: Multimedia :: Sound/Audio
Classifier: Topic :: Multimedia :: Video
Classifier: Topic :: Software Development :: Quality Assurance
Classifier: Topic :: Software Development :: Testing
Requires-Python: >=3.7
License-File: LICENSE
